notipi/__init__.py
notipi/notify_macos.py
notipi/notipi.py
notipi/utils.py
notipi/sounds/__init__.py
notipi/sounds/aurora.mp3
notipi-1.1.1.dist-info/LICENSE
notipi-1.1.1.dist-info/METADATA
notipi-1.1.1.dist-info/WHEEL
notipi-1.1.1.dist-info/entry_points.txt
notipi-1.1.1.dist-info/top_level.txt
notipi-1.1.1.dist-info/RECORD
