Metadata-Version: 2.1
Name: notipi
Version: 1.1.1
Summary: A PyPI package to deliver notifications via your own telegram bot
Author-email: Harshit Sharma <harshit158@gmail.com>
Project-URL: Homepage, https://github.com/harshit158/notipi
Project-URL: Source, https://github.com/harshit158/notipi
Requires-Python: >=3.9
License-File: LICENSE
Requires-Dist: anyio ==4.4.0
Requires-Dist: certifi ==2024.6.2
Requires-Dist: enum34 ==1.1.10
Requires-Dist: h11 ==0.14.0
Requires-Dist: httpcore ==1.0.5
Requires-Dist: httpx ==0.27.0
Requires-Dist: idna ==3.7
Requires-Dist: python-dotenv ==1.0.1
Requires-Dist: python-telegram-bot ==21.2
Requires-Dist: sniffio ==1.3.1
Requires-Dist: ipython
Requires-Dist: nest-asyncio ==1.6.0
